{
    "id": "playbooks",
    "name": "Сценарии",
    "description": "Mattermost Сценарии обеспечивает надежные и воспроизводимые процессы для ваших команд, используя чек-листы, автоматизацию и ретроспективы.",
    "homepage_url": "https://github.com/WendyH/mattermost-plugin-playbooks/",
    "support_url": "https://github.com/WendyH/mattermost-plugin-playbooks/issues",
    "icon_path": "assets/plugin_icon.svg",
    "min_server_version": "7.6.0",
    "server": {
        "executables": {
            "linux-amd64": "server/dist/plugin-linux-amd64",
            "linux-arm64": "server/dist/plugin-linux-arm64",
            "darwin-amd64": "server/dist/plugin-darwin-amd64",
            "darwin-arm64": "server/dist/plugin-darwin-arm64",
            "windows-amd64": "server/dist/plugin-windows-amd64.exe"
        }
    },
    "webapp": {
        "bundle_path": "webapp/dist/main.js"
    },
    "settings_schema": {
        "header": "",
        "footer": "",
        "settings": [
        {
            "key": "EnableExperimentalFeatures",
            "type": "bool",
            "display_name": "Включить экспериментальные функции:",
            "help_text": "Включите экспериментальные функции, которые поставляются с незавершенным пользовательским интерфейсом, ошибками и интересными вещами."
        }
        ]
    }
}
